LICENSE
MANIFEST.in
README.md
setup.cfg
setup.py
tap_toggl/__init__.py
tap_toggl/discover.py
tap_toggl/streams.py
tap_toggl/sync.py
tap_toggl/toggl.py
tap_toggl.egg-info/PKG-INFO
tap_toggl.egg-info/SOURCES.txt
tap_toggl.egg-info/dependency_links.txt
tap_toggl.egg-info/entry_points.txt
tap_toggl.egg-info/requires.txt
tap_toggl.egg-info/top_level.txt
tap_toggl/schemas/clients.json
tap_toggl/schemas/groups.json
tap_toggl/schemas/projects.json
tap_toggl/schemas/schema-fixture.json
tap_toggl/schemas/tags.json
tap_toggl/schemas/tasks.json
tap_toggl/schemas/time_entries.json
tap_toggl/schemas/users.json
tap_toggl/schemas/workspace_users.json
tap_toggl/schemas/workspaces.json