Metadata-Version: 1.1
Name: tap-toggl
Version: 1.0.2
Summary: Singer.io tap for extracting data from the Toggl API
Home-page: http://github.com/singer-io/tap-toggl
Author: Stitch
Author-email: UNKNOWN
License: UNKNOWN
Platform: UNKNOWN
Classifier: Programming Language :: Python :: 3 :: Only
